blockdata/__init__.py
blockdata/blockdata.py
blockdata-0.3.2.dist-info/LICENSE
blockdata-0.3.2.dist-info/METADATA
blockdata-0.3.2.dist-info/WHEEL
blockdata-0.3.2.dist-info/top_level.txt
blockdata-0.3.2.dist-info/RECORD
