Metadata-Version: 2.1
Name: blockdata
Version: 0.3.2
Summary: Store coordinate values as a compressed block.
Home-page: UNKNOWN
Author: Kent Kawashima
Author-email: kentkawashima@gmail.com
License: UNKNOWN
Keywords: block,bioinformatics
Platform: UNKNOWN
Classifier: Programming Language :: Python :: 3
Classifier: License :: OSI Approved :: MIT License
Classifier: Operating System :: OS Independent
